mymathutils1/__init__.py
mymathutils1/core.py
mymathutils1-0.1.0.dist-info/licenses/LICENSE
mymathutils1-0.1.0.dist-info/METADATA
mymathutils1-0.1.0.dist-info/WHEEL
mymathutils1-0.1.0.dist-info/top_level.txt
mymathutils1-0.1.0.dist-info/RECORD
