Metadata-Version: 2.4
Name: mymathutils1
Version: 0.1.0
Summary: A simple math utilities package
Author-email: Ved Tiwari <vedprakash4utiwari@example.com>
License: MIT License
Project-URL: Homepage, https://github.com/Tved1209/mymathutils1
Project-URL: Bug_Tracker, https://github.com/Tved1209/mymathutils1/issues
Requires-Python: >=3.8
License-File: LICENSE
Dynamic: license-file
